BlenderBatchExporter/__init__.py
BlenderBatchExporter/batchExportObj.py
BlenderBatchExporter/exportObj.py
BlenderBatchExporter-0.4.dist-info/entry_points.txt
BlenderBatchExporter-0.4.dist-info/LICENSE
BlenderBatchExporter-0.4.dist-info/WHEEL
BlenderBatchExporter-0.4.dist-info/METADATA
BlenderBatchExporter-0.4.dist-info/RECORD
