Metadata-Version: 2.1
Name: BlenderBatchExporter
Version: 0.4
Summary: Batch process blend files
Home-page: https://github.com/Utsira/BlenderBatchExporter
License: UNKNOWN
Author: Oliver Dew
Author-email: olidew@gmail.com
Requires-Python: >=3
Classifier: License :: OSI Approved :: MIT License
Classifier: Programming Language :: Python :: 3
